zerotouch_sdk/__init__.py
zerotouch_sdk/auth.py
zerotouch_sdk/dependencies.py
zerotouch_sdk/exceptions.py
zerotouch_sdk/middleware.py
zerotouch_sdk/models.py
zerotouch_sdk/testing.py
zerotouch_sdk_python-1.0.0.dist-info/METADATA
zerotouch_sdk_python-1.0.0.dist-info/WHEEL
zerotouch_sdk_python-1.0.0.dist-info/top_level.txt
zerotouch_sdk_python-1.0.0.dist-info/RECORD
