Metadata-Version: 2.4
Name: zerotouch-sdk-python
Version: 1.0.0
Summary: Centralized JWT validation SDK for ZeroTouch platform services
Author: ZeroTouch Platform Team
License: MIT
Classifier: Development Status :: 4 - Beta
Classifier: Intended Audience :: Developers
Classifier: License :: OSI Approved :: MIT License
Classifier: Programming Language :: Python :: 3
Classifier: Programming Language :: Python :: 3.9
Classifier: Programming Language :: Python :: 3.10
Classifier: Programming Language :: Python :: 3.11
Classifier: Programming Language :: Python :: 3.12
Classifier: Framework :: FastAPI
Requires-Python: >=3.9
Requires-Dist: PyJWT[crypto]>=2.8.0
Requires-Dist: cryptography>=41.0.0
Requires-Dist: fastapi>=0.104.0
Requires-Dist: starlette>=0.27.0
Provides-Extra: dev
Requires-Dist: pytest>=7.4.0; extra == "dev"
Requires-Dist: pytest-asyncio>=0.21.0; extra == "dev"
Requires-Dist: pytest-mock>=3.12.0; extra == "dev"
Requires-Dist: pytest-cov>=4.1.0; extra == "dev"
Requires-Dist: httpx>=0.25.0; extra == "dev"
Requires-Dist: hypothesis>=6.92.0; extra == "dev"
Provides-Extra: otel
Requires-Dist: opentelemetry-api>=1.21.0; extra == "otel"
Requires-Dist: opentelemetry-sdk>=1.21.0; extra == "otel"
